{"stat.chestOpened":12,"stat.useItem.minecraft.bow":135,"stat.useItem.minecraft.painting":1,"stat.pigOneCm":439343,"stat.leaveGame":26,"stat.useItem.minecraft.log2":52,"stat.useItem.minecraft.diamond_axe":2,"stat.mineBlock.minecraft.deadbush":5,"stat.useItem.minecraft.diamond_sword":15,"stat.useItem.minecraft.carpet":8,"stat.useItem.minecraft.potion":143,"stat.mineBlock.minecraft.stained_glass_pane":3,"stat.useItem.minecraft.bedrock":40,"stat.jump":659,"stat.swimOneCm":2239,"stat.useItem.minecraft.sand":1,"stat.fallOneCm":24021,"stat.useItem.minecraft.planks":177,"stat.climbOneCm":2206,"achievement.buildWorkBench":2,"stat.crouchOneCm":572,"stat.enderchestOpened":2,"stat.mineBlock.minecraft.chest":3,"stat.craftItem.minecraft.chest":1,"stat.useItem.minecraft.dirt":1,"achievement.exploreAllBiomes":{"value":0,"progress":["Savanna Plateau","Beach","ForestHills","Roofed Forest","Forest","River","Ocean","Plains","Desert","The End","Savanna"]},"stat.craftingTableInteraction":3,"stat.useItem.minecraft.sapling":1,"stat.mineBlock.minecraft.glass_pane":3,"stat.mineBlock.minecraft.log2":2,"stat.damageTaken":139637,"stat.useItem.minecraft.stone_brick_stairs":84,"stat.useItem.minecraft.furnace":1,"stat.craftItem.minecraft.wooden_sword":1,"stat.craftItem.minecraft.bow":1,"stat.flyOneCm":540726,"stat.entityKilledBy.Zombie":3,"stat.killEntity.Villager":1,"stat.damageDealt":630591,"stat.timeSinceDeath":16548,"stat.useItem.minecraft.crafting_table":4,"stat.useItem.minecraft.sign":4,"stat.mineBlock.minecraft.dirt":1,"stat.useItem.minecraft.spawn_egg":49,"stat.killEntity.Pig":2,"stat.walkOneCm":1045726,"stat.useItem.minecraft.torch":13,"stat.playerKills":18,"stat.useItem.minecraft.chest":5,"stat.useItem.minecraft.potato":2,"stat.useItem.minecraft.tnt":210,"stat.craftItem.minecraft.crafting_table":3,"stat.killEntity.Creeper":2,"stat.useItem.minecraft.item_frame":1,"stat.mineBlock.minecraft.wool":4,"achievement.mineWood":34,"stat.sprintOneCm":543134,"stat.craftItem.minecraft.stick":12,"stat.craftItem.minecraft.wooden_axe":1,"stat.useItem.minecraft.glass_pane":9,"stat.useItem.minecraft.dark_oak_door":3,"stat.useItem.minecraft.bed":1,"achievement.openInventory":39,"stat.craftItem.minecraft.planks":152,"stat.killEntity.Spider":1,"stat.mobKills":20,"stat.useItem.minecraft.wooden_pressure_plate":2,"stat.useItem.minecraft.stonebrick":95,"stat.mineBlock.minecraft.log":36,"stat.useItem.minecraft.bucket":6,"stat.deaths":71,"stat.drop":95,"stat.mineBlock.minecraft.leaves":12,"stat.playOneMinute":183488,"stat.useItem.minecraft.wooden_sword":5,"stat.killEntity.Zombie":4,"stat.useItem.minecraft.wooden_axe":35,"stat.mineBlock.minecraft.jukebox":1,"stat.useItem.minecraft.jukebox":1,"stat.mineBlock.minecraft.tallgrass":10,"stat.diveOneCm":8827,"stat.useItem.minecraft.web":3}